datetoken/__init__.py
datetoken/ast.py
datetoken/evaluator.py
datetoken/exceptions.py
datetoken/lexer.py
datetoken/objects.py
datetoken/parser.py
datetoken/token.py
datetoken/utils.py
datetoken-0.6.0.dist-info/LICENSE
datetoken-0.6.0.dist-info/METADATA
datetoken-0.6.0.dist-info/WHEEL
datetoken-0.6.0.dist-info/top_level.txt
datetoken-0.6.0.dist-info/RECORD
