Metadata-Version: 2.1
Name: datetoken
Version: 0.6.0
Summary: Convert relative string tokens into datetime objects
Home-page: https://pypi.org/project/datetoken/
Author: Marcos Sanchez
Author-email: marsanben92@gmail.com
Maintainer: Marcos Sanchez
Maintainer-email: marsanben92@gmail.com
License: MIT
Project-URL: Code, https://github.com/sonirico/datetoken/
Project-URL: Issue tracker, https://github.com/sonirico/datetoken/issues
Platform: any
Requires-Python: >=2.7,!=3.0.*,!=3.1.*,!=3.2.*,!=3.3.*
License-File: LICENSE
Requires-Dist: pytz (<2021.4,>=2018.04)
Requires-Dist: python-dateutil (<2.8.2,>=2.7.3)
Provides-Extra: dev
Requires-Dist: pytest (>=3) ; extra == 'dev'
Requires-Dist: freezegun (==1.0.0) ; extra == 'dev'
Requires-Dist: coverage ; extra == 'dev'
Requires-Dist: tox ; extra == 'dev'
Provides-Extra: docs
